{
  "users":[
      {
      "userName": "Cam Newton",
      "password": "panthers",
      "favrs": [
        {
          "name": "Mark B.",
          "task": "Cook Dinner",
          "id": "favr1",
          "date": "2016-02-04"
        },
        {
          "name": "Tim K.",
          "task": "Do Dishes",
          "id": "favr2",
          "date": "2016-02-01"
        },
        {
          "name": "Ron W.",
          "task": "Clean Clothes",
          "id": "favr3",
          "date": "2016-03-21"
        },
        {
          "name": "Latavius L.",
          "task": "Get Groceries",
          "id": "favr4",
          "date": "2016-04-20"
        }
      ],
      "completed": [
        {
          "name": "Tyler T.",
          "task": "Serenade",
          "id": "favr5",
          "date": "2016-01-03"
        }
      ],
      "incoming":[
        {
          "name": "Adam C.", 
          "task": "Fix cupboard",
          "id": "favr6",
          "date": "2016-03-23"
        }
      ]

    }
  ]
}
